Workbook

Sheet 1. BvA Variance
A1: BUDGET VS. ACTUAL VARIANCE ANALYSIS - TechFlow Solutions d.o.o | FY 2024
A4: Category | B4: Jan | C4: Feb | D4: Mar | E4: Apr | F4: May | G4: Jun | H4: Jul | I4: Aug | J4: Sep | K4: Oct | L4: Nov | M4: Dec | N4: YTD Budget | O4: YTD Actual | P4: YTD Var ($) | Q4: YTD Var (%) | R4: Status | S4: Type
A5: REVENUE
A6: Subscription Revenue - Budget | B6: 400000 | C6: =B6*1.03 -> 412000 | D6: =C6*1.03 -> 424360 | E6: =D6*1.03 -> 437090.8 | F6: =E6*1.03 -> 450203.52 | G6: =F6*1.03 -> 463709.63 | H6: =G6*1.03 -> 477620.92 | I6: =H6*1.03 -> 491949.55 | J6: =I6*1.03 -> 506708.03 | K6: =J6*1.03 -> 521909.27 | L6: 180000 | M6: 185000 | N6: =SUM(B6:M6) -> 4950551.7 | O6: =SUM(B7:M7) -> 5173400 | P6: =O6-N6 -> 222848.28 | Q6: =IF(N6=0,0,P6/N6) -> 0.045014836 | R6: =IF(Q6>=0,"✓ Favorable",IF(Q6<-0.1,"✗ Unfavorable","— Neutral")) -> ✓ Favorable | S6: Budget
A7: Subscription Revenue - Actual | B7: =400*1000 -> 400000 | C7: =400*1003 -> 401200 | D7: =400*1007 -> 402800 | E7: =400*1020 -> 408000 | F7: =400*1050 -> 420000 | G7: =400*1100 -> 440000 | H7: =400*1200 -> 480000 | I7: =400*1500 -> 600000 | J7: =400*1500 -> 600000 | K7: =400*1600 -> 640000 | L7: 189000 | M7: 192400 | S7: Actual
A8: Subscription Variance | B8: =B7-B6 -> 0 | C8: =C7-C6 -> -10800 | D8: =D7-D6 -> -21560 | E8: =E7-E6 -> -29090.8 | F8: =F7-F6 -> -30203.524 | G8: =G7-G6 -> -23709.63 | H8: =H7-H6 -> 2379.0814 | I8: =I7-I6 -> 108050.45 | ... M8: =M7-M6 -> 7400 | S8: Variance
A9: Professional Services - Budget | B9: =280*100 -> 28000 | C9: =B9*1.03 -> 28840 | D9: =C9*1.03 -> 29705.2 | E9: =D9*1.03 -> 30596.356 | F9: =E9*1.03 -> 31514.247 | G9: =F9*1.03 -> 32459.674 | H9: =G9*1.03 -> 33433.464 | I9: =H9*1.03 -> 34436.468 | J9: =I9*1.03 -> 35469.562 | ... M9: =L9*1.03 -> 38758.548 | N9: =SUM(B9:M9) -> 397376.83 | O9: =SUM(B10:M10) -> 384040 | P9: =O9-N9 -> -13336.828 | Q9: =IF(N9=0,0,P9/N9) -> -0.033562168 | R9: =IF(Q9>=0,"✓ Favorable",IF(Q9<-0.1,"✗ Unfavorable","— Neutral")) -> — Neutral | S9: Budget
A10: Professional Services - Actual | B10: 26600 | C10: 31900 | D10: 34560 | E10: 28500 | F10: 33480 | G10: 31350 | H10: 30740 | I10: 32100 | J10: 36720 | K10: 33250 | L10: 34880 | M10: 29960 | S10: Actual
A11: Prof Services Variance | B11: =B10-B9 -> -1400 | C11: =C10-C9 -> 3060 | D11: =D10-D9 -> 4854.8 | E11: =E10-E9 -> -2096.356 | F11: =F10-F9 -> 1965.7533 | G11: =G10-G9 -> -1109.6741 | H11: =H10-H9 -> -2693.4643 | I11: =I10-I9 -> -2336.4682 | ... M11: =M10-M9 -> -8798.5484 | S11: Variance
A12: Other Revenue - Budget | B12: 7000 | C12: 7500 | D12: 8000 | E12: 7500 | F12: 8000 | G12: 8500 | H12: 7000 | I12: 7500 | J12: 9000 | K12: 9500 | L12: 8000 | M12: 7500 | N12: =SUM(B12:M12) -> 95000 | O12: =SUM(B13:M13) -> 97915 | P12: =O12-N12 -> 2915 | Q12: =IF(N12=0,0,P12/N12) -> 0.030684211 | R12: =IF(Q12>=0,"✓ Favorable",IF(Q12<-0.1,"✗ Unfavorable","— Neutral")) -> ✓ Favorable | S12: Budget
A13: Other Revenue - Actual | B13: 7350 | C13: 7125 | D13: 8640 | E13: 7875 | F13: 8560 | G13: 8075 | H13: 7420 | I13: 7875 | J13: 9540 | K13: 9025 | L13: 8480 | M13: 7950 | S13: Actual
A14: Other Revenue Variance | B14: =B13-B12 -> 350 | C14: =C13-C12 -> -375 | D14: =D13-D12 -> 640 | E14: =E13-E12 -> 375 | F14: =F13-F12 -> 560 | G14: =G13-G12 -> -425 | H14: =H13-H12 -> 420 | I14: =I13-I12 -> 375 | ... M14: =M13-M12 -> 450 | S14: Variance
A15: TOTAL REVENUE | B15: =B6+B9+B12 -> 435000 | C15: =C6+C9+C12 -> 448340 | D15: =D6+D9+D12 -> 462065.2 | E15: =E6+E9+E12 -> 475187.16 | F15: =F6+F9+F12 -> 489717.77 | G15: =G6+G9+G12 -> 504669.3 | H15: =H6+H9+H12 -> 518054.38 | I15: =I6+I9+I12 -> 533886.01 | ... O15: =O6+O9+O12 -> 5655355 | P15: =O15-N15 -> 212426.45 | Q15: =IF(N15=0,0,P15/N15) -> 0.039027969 | R15: =IF(Q15>=0,"✓ Favorable",IF(Q15<-0.1,"✗ Unfavorable","— Neutral")) -> ✓ Favorable | S15: Total
A16: Total Revenue - Actual | B16: =B7+B10+B13 -> 433950 | C16: =C7+C10+C13 -> 440225 | D16: =D7+D10+D13 -> 446000 | E16: =E7+E10+E13 -> 444375 | F16: =F7+F10+F13 -> 462040 | G16: =G7+G10+G13 -> 479425 | H16: =H7+H10+H13 -> 518160 | I16: =I7+I10+I13 -> 639975 | ... M16: =M7+M10+M13 -> 230310 | S16: Total
A18: EXPENSES
A19: Salaries & Benefits - Budget | B19: 95000 | C19: 95000 | D19: 96000 | E19: 98000 | F19: 99000 | G19: 100000 | H19: 102000 | I19: 103000 | J19: 105000 | K19: 107000 | L19: 108000 | M19: 110000 | N19: =SUM(B19:M19) -> 1218000 | O19: =SUM(B20:M20) -> 1223120 | P19: =O19-N19 -> 5120 | Q19: =IF(N19=0,0,P19/N19) -> 0.0042036125 | R19: =IF(Q19<=0,"✓ Favorable",IF(Q19>0.1,"✗ Unfavorable","— Neutral")) -> — Neutral | S19: Budget
A20: Salaries & Benefits - Actual | B20: 93100 | C20: 96900 | D20: 94080 | E20: 100940 | F20: 97020 | G20: 103000 | H20: 99960 | I20: 105060 | J20: 103950 | K20: 109970 | L20: 105840 | M20: 113300 | S20: Actual
A21: Salaries Variance | B21: =B20-B19 -> -1900 | C21: =C20-C19 -> 1900 | D21: =D20-D19 -> -1920 | E21: =E20-E19 -> 2940 | F21: =F20-F19 -> -1980 | G21: =G20-G19 -> 3000 | H21: =H20-H19 -> -2040 | I21: =I20-I19 -> 2060 | ... M21: =M20-M19 -> 3300 | S21: Variance
A22: Marketing - Budget | B22: 18000 | C22: 19000 | D22: 20000 | E22: 21000 | F22: 22000 | G22: 20000 | H22: 18000 | I22: 19000 | J22: 22000 | K22: 24000 | L22: 23000 | M22: 20000 | N22: =SUM(B22:M22) -> 246000 | O22: =SUM(B23:M23) -> 252500 | P22: =O22-N22 -> 6500 | Q22: =IF(N22=0,0,P22/N22) -> 0.026422764 | R22: =IF(Q22<=0,"✓ Favorable",IF(Q22>0.1,"✗ Unfavorable","— Neutral")) -> — Neutral | S22: Budget
A23: Marketing - Actual | B23: 19260 | C23: 18050 | D23: 21400 | E23: 19950 | F23: 23540 | G23: 19200 | H23: 19080 | I23: 20330 | J23: 23320 | K23: 22560 | L23: 24610 | M23: 21200 | S23: Actual
A24: Marketing Variance | B24: =B23-B22 -> 1260 | C24: =C23-C22 -> -950 | D24: =D23-D22 -> 1400 | E24: =E23-E22 -> -1050 | F24: =F23-F22 -> 1540 | G24: =G23-G22 -> -800 | H24: =H23-H22 -> 1080 | I24: =I23-I22 -> 1330 | ... M24: =M23-M22 -> 1200 | S24: Variance
A25: R&D - Budget | B25: 25000 | C25: 25500 | D25: 26000 | E25: 26500 | F25: 27000 | G25: 27500 | H25: 28000 | I25: 28500 | J25: 29000 | K25: 29500 | L25: 30000 | M25: 30500 | N25: =SUM(B25:M25) -> 333000 | O25: =SUM(B26:M26) -> 336110 | P25: =O25-N25 -> 3110 | Q25: =IF(N25=0,0,P25/N25) -> 0.0093393393 | R25: =IF(Q25<=0,"✓ Favorable",IF(Q25>0.1,"✗ Unfavorable","— Neutral")) -> — Neutral | S25: Budget
A26: R&D - Actual | B26: 24250 | C26: 26775 | D26: 25480 | E26: 27825 | F26: 26190 | G26: 28875 | H26: 27160 | I26: 29925 | J26: 28130 | K26: 30680 | L26: 29100 | M26: 31720 | S26: Actual
A27: R&D Variance | B27: =B26-B25 -> -750 | C27: =C26-C25 -> 1275 | D27: =D26-D25 -> -520 | E27: =E26-E25 -> 1325 | F27: =F26-F25 -> -810 | G27: =G26-G25 -> 1375 | H27: =H26-H25 -> -840 | I27: =I26-I25 -> 1425 | ... M27: =M26-M25 -> 1220 | S27: Variance
A28: Operations - Budget | B28: 12000 | C28: 12000 | D28: 12500 | E28: 12500 | F28: 13000 | G28: 13000 | H28: 13500 | I28: 13500 | J28: 14000 | K28: 14000 | L28: 14500 | M28: 14500 | N28: =SUM(B28:M28) -> 159000 | O28: =SUM(B29:M29) -> 159795 | P28: =O28-N28 -> 795 | Q28: =IF(N28=0,0,P28/N28) -> 0.005 | R28: =IF(Q28<=0,"✓ Favorable",IF(Q28>0.1,"✗ Unfavorable","— Neutral")) -> — Neutral | S28: Budget
A29: Operations - Actual | B29: 11640 | C29: 12480 | D29: 12125 | E29: 13000 | F29: 12610 | G29: 13520 | H29: 13095 | I29: 14040 | J29: 13580 | K29: 14560 | L29: 14065 | M29: 15080 | S29: Actual
A30: Operations Variance | B30: =B29-B28 -> -360 | C30: =C29-C28 -> 480 | D30: =D29-D28 -> -375 | E30: =E29-E28 -> 500 | F30: =F29-F28 -> -390 | G30: =G29-G28 -> 520 | H30: =H29-H28 -> -405 | I30: =I29-I28 -> 540 | ... M30: =M29-M28 -> 580 | S30: Variance
A31: G&A - Budget | B31: 8000 | C31: 8000 | D31: 8200 | E31: 8200 | F31: 8400 | G31: 8400 | H31: 8600 | I31: 8600 | J31: 8800 | K31: 8800 | L31: 9000 | M31: 9000 | N31: =SUM(B31:M31) -> 102000 | O31: =SUM(B32:M32) -> 102510 | P31: =O31-N31 -> 510 | Q31: =IF(N31=0,0,P31/N31) -> 0.005 | R31: =IF(Q31<=0,"✓ Favorable",IF(Q31>0.1,"✗ Unfavorable","— Neutral")) -> — Neutral | S31: Budget
A32: G&A - Actual | B32: 7760 | C32: 8320 | D32: 7954 | E32: 8528 | F32: 8148 | G32: 8736 | H32: 8342 | I32: 8944 | J32: 8536 | K32: 9152 | L32: 8730 | M32: 9360 | S32: Actual
A33: G&A Variance | B33: =B32-B31 -> -240 | C33: =C32-C31 -> 320 | D33: =D32-D31 -> -246 | E33: =E32-E31 -> 328 | F33: =F32-F31 -> -252 | G33: =G32-G31 -> 336 | H33: =H32-H31 -> -258 | I33: =I32-I31 -> 344 | ... M33: =M32-M31 -> 360 | S33: Variance
A34: TOTAL EXPENSES | B34: =B19+B22+B25+B28+B31 -> 158000 | C34: =C19+C22+C25+C28+C31 -> 159500 | D34: =D19+D22+D25+D28+D31 -> 162700 | E34: =E19+E22+E25+E28+E31 -> 166200 | F34: =F19+F22+F25+F28+F31 -> 169400 | G34: =G19+G22+G25+G28+G31 -> 168900 | H34: =H19+H22+H25+H28+H31 -> 170100 | I34: =I19+I22+I25+I28+I31 -> 172600 | ... O34: =O19+O22+O25+O28+O31 -> 2074035 | P34: =O34-N34 -> 16035 | Q34: =IF(N34=0,0,P34/N34) -> 0.0077915452 | R34: =IF(Q34<=0,"✓ Favorable",IF(Q34>0.1,"✗ Unfavorable","— Neutral")) -> — Neutral | S34: Total
A35: Total Expenses - Actual | B35: =B20+B23+B26+B29+B32 -> 156010 | C35: =C20+C23+C26+C29+C32 -> 162525 | D35: =D20+D23+D26+D29+D32 -> 161039 | E35: =E20+E23+E26+E29+E32 -> 170243 | F35: =F20+F23+F26+F29+F32 -> 167508 | G35: =G20+G23+G26+G29+G32 -> 173331 | H35: =H20+H23+H26+H29+H32 -> 167637 | I35: =I20+I23+I26+I29+I32 -> 178299 | ... M35: =M20+M23+M26+M29+M32 -> 190660 | S35: Total
A37: NET INCOME
A38: Net Income - Budget | B38: =B15-B34 -> 277000 | C38: =C15-C34 -> 288840 | D38: =D15-D34 -> 299365.2 | E38: =E15-E34 -> 308987.16 | F38: =F15-F34 -> 320317.77 | G38: =G15-G34 -> 335769.3 | H38: =H15-H34 -> 347954.38 | I38: =I15-I34 -> 361286.01 | ... M38: =M15-M34 -> 47258.548 | N38: =SUM(B38:M38) -> 3384928.6 | O38: =SUM(B39:M39) -> 3581320 | P38: =O38-N38 -> 196391.45 | Q38: =IF(N38=0,0,P38/N38) -> 0.058019378 | R38: =IF(Q38>=0,"✓ Favorable",IF(Q38<-0.1,"✗ Unfavorable","— Neutral")) -> ✓ Favorable | S38: Budget
A39: Net Income - Actual | B39: =B16-B35 -> 277940 | C39: =C16-C35 -> 277700 | D39: =D16-D35 -> 284961 | E39: =E16-E35 -> 274132 | F39: =F16-F35 -> 294532 | G39: =G16-G35 -> 306094 | H39: =H16-H35 -> 350523 | I39: =I16-I35 -> 461676 | ... M39: =M16-M35 -> 39650 | S39: Actual

Sheet 2. Headcount Planning
A1: HEADCOUNT & PERSONNEL PLANNING MODEL - TechFlow Solutions d.o.o. | FY 2024
A4: Department | B4: Start HC | C4: Q1 Hires | D4: Q1 Dept | E4: Q1 End | F4: Q2 Hires | G4: Q2 Dept | H4: Q2 End | I4: Q3 Hires | J4: Q3 Dept | K4: Q3 End | L4: Q4 Hires | M4: Q4 Dept | N4: Q4 End | O4: Avg Salary ($) | P4: Benefits 25% | Q4: Total Cost/FTE | R4: Annual Cost ($)
A5: Sales | B5: 8 | C5: 1 | D5: 0 | E5: =B5+C5-D5 -> 9 | F5: 2 | G5: 0 | H5: =E5+F5-G5 -> 11 | I5: 1 | J5: 1 | K5: =H5+I5-J5 -> 11 | L5: 1 | M5: 0 | N5: =K5+L5-M5 -> 12 | O5: 45000 | P5: =O5*0.25 -> 11250 | Q5: =O5+P5 -> 56250 | R5: =AVERAGE(B5,E5,H5,K5,N5)*Q5 -> 573750
A6: Marketing | B6: 6 | C6: 1 | D6: 0 | E6: =B6+C6-D6 -> 7 | F6: 1 | G6: 0 | H6: =E6+F6-G6 -> 8 | I6: 0 | J6: 0 | K6: =H6+I6-J6 -> 8 | L6: 1 | M6: 0 | N6: =K6+L6-M6 -> 9 | O6: 42000 | P6: =O6*0.25 -> 10500 | Q6: =O6+P6 -> 52500 | R6: =AVERAGE(B6,E6,H6,K6,N6)*Q6 -> 399000
A7: Product/Engineering | B7: 18 | C7: 2 | D7: 0 | E7: =B7+C7-D7 -> 20 | F7: 2 | G7: 1 | H7: =E7+F7-G7 -> 21 | I7: 2 | J7: 0 | K7: =H7+I7-J7 -> 23 | L7: 1 | M7: 0 | N7: =K7+L7-M7 -> 24 | O7: 55000 | P7: =O7*0.25 -> 13750 | Q7: =O7+P7 -> 68750 | R7: =AVERAGE(B7,E7,H7,K7,N7)*Q7 -> 1457500
A8: Customer Success | B8: 7 | C8: 1 | D8: 0 | E8: =B8+C8-D8 -> 8 | F8: 1 | G8: 0 | H8: =E8+F8-G8 -> 9 | I8: 1 | J8: 0 | K8: =H8+I8-J8 -> 10 | L8: 0 | M8: 0 | N8: =K8+L8-M8 -> 10 | O8: 38000 | P8: =O8*0.25 -> 9500 | Q8: =O8+P8 -> 47500 | R8: =AVERAGE(B8,E8,H8,K8,N8)*Q8 -> 418000
A9: G&A | B9: 6 | C9: 0 | D9: 0 | E9: =B9+C9-D9 -> 6 | F9: 1 | G9: 0 | H9: =E9+F9-G9 -> 7 | I9: 0 | J9: 0 | K9: =H9+I9-J9 -> 7 | L9: 1 | M9: 1 | N9: =K9+L9-M9 -> 7 | O9: 48000 | P9: =O9*0.25 -> 12000 | Q9: =O9+P9 -> 60000 | R9: =AVERAGE(B9,E9,H9,K9,N9)*Q9 -> 396000
A10: TOTAL | B10: =SUM(B5:B9) -> 45 | C10: =SUM(C5:C9) -> 5 | D10: =SUM(D5:D9) -> 0 | E10: =SUM(E5:E9) -> 50 | F10: =SUM(F5:F9) -> 7 | G10: =SUM(G5:G9) -> 1 | H10: =SUM(H5:H9) -> 56 | I10: =SUM(I5:I9) -> 4 | ... N10: =SUM(N5:N9) -> 62 | O10: =AVERAGE(O5:O9) -> 45600 | P10: =AVERAGE(P5:P9) -> 11400 | Q10: =AVERAGE(Q5:Q9) -> 57000 | R10: =SUM(R5:R9) -> 3244250
A12: FTE SUMMARY
A13: Metric | B13: Q1 | C13: Q2 | D13: Q3 | E13: Q4 | F13: Full Year
A14: Beginning Headcount | B14: =B10 -> 45 | C14: =E10 -> 50 | D14: =H10 -> 56 | E14: =K10 -> 59 | F14: =B10 -> 45
A15: Total Hires | B15: =C10 -> 5 | C15: =F10 -> 7 | D15: =I10 -> 4 | E15: =L10 -> 4 | F15: =SUM(B15:E15) -> 20
A16: Total Departures | B16: =D10 -> 0 | C16: =G10 -> 1 | D16: =J10 -> 1 | E16: =M10 -> 1 | F16: =SUM(B16:E16) -> 3
A17: Ending Headcount | B17: =E10 -> 50 | C17: =H10 -> 56 | D17: =K10 -> 59 | E17: =N10 -> 62 | F17: =N10 -> 62
A18: Average FTE | B18: =AVERAGE(B14,B17) -> 47.5 | C18: =AVERAGE(C14,C17) -> 53 | D18: =AVERAGE(D14,D17) -> 57.5 | E18: =AVERAGE(E14,E17) -> 60.5 | F18: =AVERAGE(B18:E18) -> 54.625
A20: PERSONNEL COST BREAKDOWN
A21: Department | B21: Q1 Cost | C21: Q2 Cost | D21: Q3 Cost | E21: Q4 Cost | F21: Annual Cost
A22: Sales | B22: =AVERAGE(B5,E5)*$Q$5/4 -> 119531.25 | C22: =AVERAGE(E5,H5)*$Q$5/4 -> 140625 | D22: =AVERAGE(H5,K5)*$Q$5/4 -> 154687.5 | E22: =AVERAGE(K5,N5)*$Q$5/4 -> 161718.75 | F22: =SUM(B22:E22) -> 576562.5
A23: Marketing | B23: =AVERAGE(B6,E6)*$Q$6/4 -> 85312.5 | C23: =AVERAGE(E6,H6)*$Q$6/4 -> 98437.5 | D23: =AVERAGE(H6,K6)*$Q$6/4 -> 105000 | E23: =AVERAGE(K6,N6)*$Q$6/4 -> 111562.5 | F23: =SUM(B23:E23) -> 400312.5
A24: Product/Engineering | B24: =AVERAGE(B7,E7)*$Q$7/4 -> 326562.5 | C24: =AVERAGE(E7,H7)*$Q$7/4 -> 352343.75 | D24: =AVERAGE(H7,K7)*$Q$7/4 -> 378125 | E24: =AVERAGE(K7,N7)*$Q$7/4 -> 403906.25 | F24: =SUM(B24:E24) -> 1460937.5
A25: Customer Success | B25: =AVERAGE(B8,E8)*$Q$8/4 -> 89062.5 | C25: =AVERAGE(E8,H8)*$Q$8/4 -> 100937.5 | D25: =AVERAGE(H8,K8)*$Q$8/4 -> 112812.5 | E25: =AVERAGE(K8,N8)*$Q$8/4 -> 118750 | F25: =SUM(B25:E25) -> 421562.5
A26: G&A | B26: =AVERAGE(B9,E9)*$Q$9/4 -> 90000 | C26: =AVERAGE(E9,H9)*$Q$9/4 -> 97500 | D26: =AVERAGE(H9,K9)*$Q$9/4 -> 105000 | E26: =AVERAGE(K9,N9)*$Q$9/4 -> 105000 | F26: =SUM(B26:E26) -> 397500
A27: TOTAL PERSONNEL COST | B27: =SUM(B22:B26) -> 710468.75 | C27: =SUM(C22:C26) -> 789843.75 | D27: =SUM(D22:D26) -> 855625 | E27: =SUM(E22:E26) -> 900937.5 | F27: =SUM(F22:F26) -> 3256875

Sheet 3. Revenue Forecast
A1: REVENUE FORECASTING MODEL - TechFlow Solutions d.o.o. | FY 2024
A4: KEY ASSUMPTIONS
A5: Metric | B5: Value | C5: Notes
A6: Starting MRR (Jan) | B6: 150000 | C6: Base subscription revenue
A7: Monthly Churn Rate | B7: 0.04 | C7: Lost MRR % monthly
A8: Expansion Rate | B8: 0.03 | C8: Upsell/cross-sell %
A9: Avg New MRR/Month | B9: 12000 | C9: New customer acquisition
A11: MRR WATERFALL MODEL
A12: Metric | B12: Jan | C12: Feb | D12: Mar | E12: Apr | F12: May | G12: Jun | H12: Jul | I12: Aug | J12: Sep | K12: Oct | L12: Nov | M12: Dec | N12: YTD Total | O12: ARR
A13: Beginning MRR | B13: =$B$6 -> 150000 | C13: =B18 -> 158500 | D13: =C18 -> 168415 | E13: =D18 -> 179730.85 | F13: =E18 -> 189933.54 | G13: =F18 -> 202034.21 | H13: =G18 -> 211013.86 | I13: =H18 -> 217903.73 | J13: =I18 -> 228224.69 | ... M13: =L18 -> 264002.69
A14: (+) New MRR | B14: 10000 | C14: 11500 | D14: 13000 | E14: 12000 | F14: 14000 | G14: 11000 | H14: 9000 | I14: 12500 | J14: 15000 | K14: 14500 | L14: 13500 | M14: 11000 | N14: =SUM(B14:M14) -> 147000
A15: (+) Expansion MRR | B15: =B13*$B$8 -> 4500 | C15: =C13*$B$8 -> 4755 | D15: =D13*$B$8 -> 5052.45 | E15: =E13*$B$8 -> 5391.9255 | F15: =F13*$B$8 -> 5698.0062 | G15: =G13*$B$8 -> 6061.0262 | H15: =H13*$B$8 -> 6330.4159 | I15: =I13*$B$8 -> 6537.1118 | ... M15: =M13*$B$8 -> 7920.0806 | N15: =SUM(B15:M15) -> 73912.021
A16: (-) Churned MRR | B16: =-B13*$B$7 -> -6000 | C16: =-C13*$B$7 -> -6340 | D16: =-D13*$B$7 -> -6736.6 | E16: =-E13*$B$7 -> -7189.234 | F16: =-F13*$B$7 -> -7597.3417 | G16: =-G13*$B$7 -> -8081.3682 | H16: =-H13*$B$7 -> -8440.5546 | I16: =-I13*$B$7 -> -8716.149 | ... M16: =-M13*$B$7 -> -10560.107 | N16: =SUM(B16:M16) -> -98549.361
A17: Net MRR Change | B17: =B14+B15+B16 -> 8500 | C17: =C14+C15+C16 -> 9915 | D17: =D14+D15+D16 -> 11315.85 | E17: =E14+E15+E16 -> 10202.692 | F17: =F14+F15+F16 -> 12100.665 | G17: =G14+G15+G16 -> 8979.6579 | H17: =H14+H15+H16 -> 6889.8614 | I17: =I14+I15+I16 -> 10320.963 | ... M17: =M14+M15+M16 -> 8359.9731 | N17: =SUM(B17:M17) -> 122362.66
A18: Ending MRR | B18: =B13+B17 -> 158500 | C18: =C13+C17 -> 168415 | D18: =D13+D17 -> 179730.85 | E18: =E13+E17 -> 189933.54 | F18: =F13+F17 -> 202034.21 | G18: =G13+G17 -> 211013.86 | H18: =H13+H17 -> 217903.73 | I18: =I13+I17 -> 228224.69 | ... M18: =M13+M17 -> 272362.66 | N18: =M18 -> 272362.66 | O18: =M18*12 -> 3268351.9
A19: MoM Growth % | B19: - | C19: =(C18-B18)/B18 -> 0.062555205 | D19: =(D18-C18)/C18 -> 0.067190274 | E19: =(E18-D18)/D18 -> 0.056766501 | F19: =(F18-E18)/E18 -> 0.063709993 | G19: =(G18-F18)/F18 -> 0.044446226 | H19: =(H18-G18)/G18 -> 0.032651226 | I19: =(I18-H18)/H18 -> 0.047364783 | J19: =(J18-I18)/I18 -> 0.055724704 | ... M19: =(M18-L18)/L18 -> 0.031666243 | N19: =(M18-B13)/B13 -> 0.81575107
A21: TOTAL REVENUE SUMMARY
A22: Revenue Stream | B22: Jan | C22: Feb | D22: Mar | E22: Apr | F22: May | G22: Jun | H22: Jul | I22: Aug | J22: Sep | K22: Oct | L22: Nov | M22: Dec | N22: Annual Total | O22: % of Rev
A23: Subscription Revenue | B23: =B18 -> 158500 | C23: =C18 -> 168415 | D23: =D18 -> 179730.85 | E23: =E18 -> 189933.54 | F23: =F18 -> 202034.21 | G23: =G18 -> 211013.86 | H23: =H18 -> 217903.73 | I23: =I18 -> 228224.69 | ... M23: =M18 -> 272362.66 | N23: =SUM(B23:M23) -> 2586096.7 | O23: =N23/N26 -> 0.84954486
A24: Professional Services | B24: 28000 | C24: 31000 | D24: 35000 | E24: 29000 | F24: 33000 | G24: 32000 | H24: 27000 | I24: 30000 | J24: 34000 | K24: 32000 | L24: 31000 | M24: 26000 | N24: =SUM(B24:M24) -> 368000 | O24: =N24/N26 -> 0.12088972
A25: One-Time Fees | B25: 5000 | C25: 7500 | D25: 8000 | E25: 6000 | F25: 9500 | G25: 7000 | H25: 5500 | I25: 8500 | J25: 10000 | K25: 9000 | L25: 7500 | M25: 6500 | N25: =SUM(B25:M25) -> 90000 | O25: =N25/N26 -> 0.029565421
A26: TOTAL REVENUE | B26: =SUM(B23:B25) -> 191500 | C26: =SUM(C23:C25) -> 206915 | D26: =SUM(D23:D25) -> 222730.85 | E26: =SUM(E23:E25) -> 224933.54 | F26: =SUM(F23:F25) -> 244534.21 | G26: =SUM(G23:G25) -> 250013.86 | H26: =SUM(H23:H25) -> 250403.73 | I26: =SUM(I23:I25) -> 266724.69 | ... N26: =SUM(N23:N25) -> 3044096.7 | O26: =N26/N26 -> 1
A27: MoM Revenue Growth | B27: - | C27: =(C26-B26)/B26 -> 0.080496084 | D27: =(D26-C26)/C26 -> 0.076436459 | E27: =(E26-D26)/D26 -> 0.0098894765 | F27: =(F26-E26)/E26 -> 0.087139803 | G27: =(G26-F26)/F26 -> 0.022408554 | H27: =(H26-G26)/G26 -> 0.001559359 | I27: =(I26-H26)/H26 -> 0.065178594 | J27: =(J26-I26)/I26 -> 0.068301713 | ... M27: =(M26-L26)/L26 -> 0.0078014948 | N27: =(M26-B26)/B26 -> 0.59197211

Sheet 4. Rolling Forecast
A1: 12-MONTH ROLLING FORECAST - TechFlow Solutions d.o.o. | Feb 2024 - Jan 2025
A4: Category | B4: 46077 | C4: 46105 | D4: 46136 | E4: 46166 | F4: 46197 | G4: 46227 | H4: 46258 | I4: 46289 | J4: 46319 | K4: 46350 | L4: 46380 | M4: 46047 | N4: 12M Total | O4: Budget | P4: Var %
A5: REVENUE
A6: Subscription Revenue | B6: ='3. Revenue Forecast'!C23*1.05 -> 176835.75 | C6: ='3. Revenue Forecast'!D23*1.05 -> 188717.39 | D6: ='3. Revenue Forecast'!E23*1.05 -> 199430.22 | E6: ='3. Revenue Forecast'!F23*1.05 -> 212135.92 | F6: ='3. Revenue Forecast'!G23*1.05 -> 221564.56 | G6: ='3. Revenue Forecast'!H23*1.05 -> 228798.91 | H6: ='3. Revenue Forecast'!I23*1.05 -> 239635.92 | I6: ='3. Revenue Forecast'!J23*1.05 -> 252989.56 | ... L6: ='3. Revenue Forecast'!M23*1.05 -> 285980.79 | M6: =L6*1.04 -> 297420.02 | N6: =SUM(B6:M6) -> 2846396.5 | O6: 1966000 | P6: =(N6-O6)/O6 -> 0.44781106
A7: Professional Services | B7: ='3. Revenue Forecast'!C24*1.05 -> 32550 | C7: ='3. Revenue Forecast'!D24*1.05 -> 36750 | D7: ='3. Revenue Forecast'!E24*1.05 -> 30450 | E7: ='3. Revenue Forecast'!F24*1.05 -> 34650 | F7: ='3. Revenue Forecast'!G24*1.05 -> 33600 | G7: ='3. Revenue Forecast'!H24*1.05 -> 28350 | H7: ='3. Revenue Forecast'!I24*1.05 -> 31500 | I7: ='3. Revenue Forecast'!J24*1.05 -> 35700 | ... L7: ='3. Revenue Forecast'!M24*1.05 -> 27300 | M7: =L7*1.02 -> 27846 | N7: =SUM(B7:M7) -> 384846 | O7: 371000 | P7: =(N7-O7)/O7 -> 0.037320755
A8: Other Revenue | B8: ='3. Revenue Forecast'!C25*1.05 -> 7875 | C8: ='3. Revenue Forecast'!D25*1.05 -> 8400 | D8: ='3. Revenue Forecast'!E25*1.05 -> 6300 | E8: ='3. Revenue Forecast'!F25*1.05 -> 9975 | F8: ='3. Revenue Forecast'!G25*1.05 -> 7350 | G8: ='3. Revenue Forecast'!H25*1.05 -> 5775 | H8: ='3. Revenue Forecast'!I25*1.05 -> 8925 | I8: ='3. Revenue Forecast'!J25*1.05 -> 10500 | ... L8: ='3. Revenue Forecast'!M25*1.05 -> 6825 | M8: =L8*1.02 -> 6961.5 | N8: =SUM(B8:M8) -> 96211.5 | O8: 95000 | P8: =(N8-O8)/O8 -> 0.012752632
A9: TOTAL REVENUE | B9: =SUM(B6:B8) -> 217260.75 | C9: =SUM(C6:C8) -> 233867.39 | D9: =SUM(D6:D8) -> 236180.22 | E9: =SUM(E6:E8) -> 256760.92 | F9: =SUM(F6:F8) -> 262514.56 | G9: =SUM(G6:G8) -> 262923.91 | H9: =SUM(H6:H8) -> 280060.92 | I9: =SUM(I6:I8) -> 299189.56 | ... O9: =SUM(O6:O8) -> 2432000 | P9: =(N9-O9)/O9 -> 0.36819656
A11: OPERATING EXPENSES
A12: Salaries & Benefits | B12: 98000 | C12: 99500 | D12: 101000 | E12: 103000 | F12: 105000 | G12: 107500 | H12: 109000 | I12: 111000 | J12: 113500 | K12: 115000 | L12: 117000 | M12: 119000 | N12: =SUM(B12:M12) -> 1298500 | O12: 1218000 | P12: =(N12-O12)/O12 -> 0.066091954
A13: Marketing | B13: 20000 | C13: 21500 | D13: 22000 | E13: 23500 | F13: 21000 | G13: 19000 | H13: 20500 | I13: 24000 | J13: 26000 | K13: 25000 | L13: 22000 | M13: 21000 | N13: =SUM(B13:M13) -> 265500 | O13: 246000 | P13: =(N13-O13)/O13 -> 0.079268293
A14: R&D | B14: 26500 | C14: 27000 | D14: 27500 | E14: 28000 | F14: 28500 | G14: 29000 | H14: 29500 | I14: 30000 | J14: 30500 | K14: 31000 | L14: 31500 | M14: 32000 | N14: =SUM(B14:M14) -> 351000 | O14: 333000 | P14: =(N14-O14)/O14 -> 0.054054054
A15: Operations | B15: 12500 | C15: 13000 | D15: 13000 | E15: 13500 | F15: 13500 | G15: 14000 | H15: 14000 | I15: 14500 | J15: 14500 | K15: 15000 | L15: 15000 | M15: 15500 | N15: =SUM(B15:M15) -> 168000 | O15: 159000 | P15: =(N15-O15)/O15 -> 0.056603774
A16: G&A | B16: 8200 | C16: 8400 | D16: 8400 | E16: 8600 | F16: 8600 | G16: 8800 | H16: 8800 | I16: 9000 | J16: 9000 | K16: 9200 | L16: 9200 | M16: 9400 | N16: =SUM(B16:M16) -> 105600 | O16: 102000 | P16: =(N16-O16)/O16 -> 0.035294118
A17: TOTAL OPEX | B17: =SUM(B12:B16) -> 165200 | C17: =SUM(C12:C16) -> 169400 | D17: =SUM(D12:D16) -> 171900 | E17: =SUM(E12:E16) -> 176600 | F17: =SUM(F12:F16) -> 176600 | G17: =SUM(G12:G16) -> 178300 | H17: =SUM(H12:H16) -> 181800 | I17: =SUM(I12:I16) -> 188500 | ... O17: =SUM(O12:O16) -> 2058000 | P17: =(N17-O17)/O17 -> 0.06345967
A19: PROFITABILITY
A20: EBITDA | B20: =B9-B17 -> 52060.75 | C20: =C9-C17 -> 64467.393 | D20: =D9-D17 -> 64280.219 | E20: =E9-E17 -> 80160.916 | F20: =F9-F17 -> 85914.557 | G20: =G9-G17 -> 84623.912 | H20: =H9-H17 -> 98260.923 | I20: =I9-I17 -> 110689.56 | ... O20: =O9-O17 -> 374000 | P20: =(N20-O20)/ABS(O20) -> 2.0450643
A21: EBITDA Margin % | B21: =B20/B9 -> 0.23962336 | C21: =C20/C9 -> 0.27565789 | D21: =D20/D9 -> 0.27216597 | E21: =E20/E9 -> 0.31220062 | F21: =F20/F9 -> 0.3272754 | G21: =G20/G9 -> 0.32185704 | H21: =H20/H9 -> 0.35085553 | I21: =I20/I9 -> 0.36996465 | ... O21: =O20/O9 -> 0.15378289
A22: Monthly Burn Rate | B22: =IF(B20<0,-B20,0) -> 0 | C22: =IF(C20<0,-C20,0) -> 0 | D22: =IF(D20<0,-D20,0) -> 0 | E22: =IF(E20<0,-E20,0) -> 0 | F22: =IF(F20<0,-F20,0) -> 0 | G22: =IF(G20<0,-G20,0) -> 0 | H22: =IF(H20<0,-H20,0) -> 0 | I22: =IF(I20<0,-I20,0) -> 0 | ... M22: =IF(M20<0,-M20,0) -> 0 | N22: =AVERAGE(B22:M22) -> 0 | O22: Avg Burn
A23: Revenue Growth % YoY | B23: =(B9-B9/1.35)/(B9/1.35) -> 0.35 | C23: =(C9-C9/1.35)/(C9/1.35) -> 0.35 | D23: =(D9-D9/1.35)/(D9/1.35) -> 0.35 | E23: =(E9-E9/1.35)/(E9/1.35) -> 0.35 | F23: =(F9-F9/1.35)/(F9/1.35) -> 0.35 | G23: =(G9-G9/1.35)/(G9/1.35) -> 0.35 | H23: =(H9-H9/1.35)/(H9/1.35) -> 0.35 | I23: =(I9-I9/1.35)/(I9/1.35) -> 0.35 | ... M23: =(M9-M9/1.35)/(M9/1.35) -> 0.35 | N23: 0.35 | O23: Target

Sheet 5. KPI Dashboard
A1: FINANCIAL KPIs & EXECUTIVE DASHBOARD - TechFlow Solutions d.o.o. | FY 2024
A4: KEY PERFORMANCE INDICATORS | G4: MONTHLY REVENUE TREND
A5: Metric | B5: Current | C5: Target | D5: Status | E5: Trend | G5: Month | H5: MRR | I5: Total Rev | J5: Growth
A6: Monthly Recurring Revenue (MRR) | B6: ='3. Revenue Forecast'!M18 -> 272362.66 | C6: 250000 | D6: =IF(B6>=C6,"✓ On Target",IF(B6>=C6*0.9,"⚠ Monitor","✗ Below")) -> ✓ On Target | E6: ↑ +5.2% | G6: Jan | H6: ='3. Revenue Forecast'!B18 -> 158500 | I6: ='3. Revenue Forecast'!B26 -> 191500 | J6: -
A7: Annual Recurring Revenue (ARR) | B7: =B6*12 -> 3268351.9 | C7: 3000000 | D7: =IF(B7>=C7,"✓ On Target",IF(B7>=C7*0.9,"⚠ Monitor","✗ Below")) -> ✓ On Target | E7: ↑ +18.5% | G7: Feb | H7: ='3. Revenue Forecast'!C18 -> 168415 | I7: ='3. Revenue Forecast'!C26 -> 206915 | J7: =(I7-I6)/I6 -> 0.080496084
A8: Customer Acquisition Cost (CAC) | B8: 1200 | C8: 1500 | D8: =IF(B8<=C8,"✓ On Target",IF(B8<=C8*1.1,"⚠ Monitor","✗ High")) -> ✓ On Target | E8: ↓ -8.3% | G8: Mar | H8: ='3. Revenue Forecast'!D18 -> 179730.85 | I8: ='3. Revenue Forecast'!D26 -> 222730.85 | J8: =(I8-I7)/I7 -> 0.076436459
A9: Customer Lifetime Value (LTV) | B9: 4500 | C9: 4000 | D9: =IF(B9>=C9,"✓ On Target",IF(B9>=C9*0.9,"⚠ Monitor","✗ Below")) -> ✓ On Target | E9: ↑ +12.5% | G9: Apr | H9: ='3. Revenue Forecast'!E18 -> 189933.54 | I9: ='3. Revenue Forecast'!E26 -> 224933.54 | J9: =(I9-I8)/I8 -> 0.0098894765
A10: LTV:CAC Ratio | B10: =B9/B8 -> 3.75 | C10: 3.0x | D10: =IF(B10>=3,"✓ On Target",IF(B10>=2,"⚠ Monitor","✗ Low")) -> ✓ On Target | E10: ↑ +0.4x | G10: May | H10: ='3. Revenue Forecast'!F18 -> 202034.21 | I10: ='3. Revenue Forecast'!F26 -> 244534.21 | J10: =(I10-I9)/I9 -> 0.087139803
A11: MRR per Employee | B11: =B6/45 -> 6052.5036 | C11: 5000 | D11: =IF(B11>=C11,"✓ On Target",IF(B11>=C11*0.9,"⚠ Monitor","✗ Below")) -> ✓ On Target | E11: ↑ +6.1% | G11: Jun | H11: ='3. Revenue Forecast'!G18 -> 211013.86 | I11: ='3. Revenue Forecast'!G26 -> 250013.86 | J11: =(I11-I10)/I10 -> 0.022408554
A12: Gross Margin % | B12: 0.78 | C12: 0.75 | D12: =IF(B12>=C12,"✓ On Target",IF(B12>=C12*0.95,"⚠ Monitor","✗ Below")) -> ✓ On Target | E12: → Stable | G12: Jul | H12: ='3. Revenue Forecast'!H18 -> 217903.73 | I12: ='3. Revenue Forecast'!H26 -> 250403.73 | J12: =(I12-I11)/I11 -> 0.001559359
A13: Net Revenue Retention (NRR) | B13: 1.12 | C13: 1.1 | D13: =IF(B13>=C13,"✓ On Target",IF(B13>=C13*0.95,"⚠ Monitor","✗ Below")) -> ✓ On Target | E13: ↑ +3.0% | G13: Aug | H13: ='3. Revenue Forecast'!I18 -> 228224.69 | I13: ='3. Revenue Forecast'!I26 -> 266724.69 | J13: =(I13-I12)/I12 -> 0.065178594
A14: Monthly Churn Rate | B14: 0.038 | C14: 0.04 | D14: =IF(B14<=C14,"✓ On Target",IF(B14<=C14*1.1,"⚠ Monitor","✗ High")) -> ✓ On Target | E14: ↓ -0.2% | G14: Sep | H14: ='3. Revenue Forecast'!J18 -> 240942.44 | I14: ='3. Revenue Forecast'!J26 -> 284942.44 | J14: =(I14-I13)/I13 -> 0.068301713
A15: Cash Balance | B15: 850000 | C15: 500000 | D15: =IF(B15>=C15,"✓ On Target",IF(B15>=C15*0.8,"⚠ Monitor","✗ Low")) -> ✓ On Target | E15: ↑ +5.0% | G15: Oct | H15: ='3. Revenue Forecast'!K18 -> 253033.02 | I15: ='3. Revenue Forecast'!K26 -> 294033.02 | J15: =(I15-I14)/I14 -> 0.0319032
A16: Cash Runway (Months) | B16: =B15/20000 -> 42.5 | C16: 12 | D16: =IF(B16>=C16,"✓ On Target",IF(B16>=C16*0.75,"⚠ Monitor","✗ Critical")) -> ✓ On Target | E16: ↑ +6 mo | G16: Nov | H16: ='3. Revenue Forecast'!L18 -> 264002.69 | I16: ='3. Revenue Forecast'!L26 -> 302502.69 | J16: =(I16-I15)/I15 -> 0.028805166
A17: Quick Ratio (SaaS) | B17: 2.8 | C17: 2 | D17: =IF(B17>=C17,"✓ On Target",IF(B17>=C17*0.8,"⚠ Monitor","✗ Low")) -> ✓ On Target | E17: ↑ +0.3 | G17: Dec | H17: ='3. Revenue Forecast'!M18 -> 272362.66 | I17: ='3. Revenue Forecast'!M26 -> 304862.66 | J17: =(I17-I16)/I16 -> 0.0078014948
A19: EXECUTIVE SUMMARY
A20: All KPIs on track | B20: 12 of 12 | C20: metrics meeting targets
A21: YTD Revenue Performance | B21: ='3. Revenue Forecast'!N26 -> 3044096.7 | C21: vs $2.43M budget | D21: =('3. Revenue Forecast'!N26-2432000)/2432000 -> 0.25168449 | E21: variance
A22: Projected Year-End ARR | B22: =B7 -> 3268351.9 | C22: from $1.8M start | D22: =(B7-1800000)/1800000 -> 0.81575107 | E22: growth
A23: Cash Position Strong | B23: =B15 -> 850000 | C23: =B16&" months runway" -> 42,5 months runway | D23: ✓ Healthy

Sheet 6. 13-Week Cash Flow
A1: 13-WEEK CASH FLOW FORECAST - TechFlow Solutions d.o.o. | Q1-Q2 2024
A4: Category | B4: Wk 1 | C4: Wk 2 | D4: Wk 3 | E4: Wk 4 | F4: Wk 5 | G4: Wk 6 | H4: Wk 7 | I4: Wk 8 | J4: Wk 9 | K4: Wk 10 | L4: Wk 11 | M4: Wk 12 | N4: Wk 13 | O4: 13W Total | P4: Avg/Wk
A5: Opening Cash Balance | B5: 850000 | C5: =B20 -> 870000 | D5: =C20 -> 785500 | E5: =D20 -> 821500 | F5: =E20 -> 738300 | G5: =F20 -> 757500 | H5: =G20 -> 672600 | I5: =H20 -> 710600 | J5: =I20 -> 625300 | ... N5: =M20 -> 518400
A7: CASH INFLOWS
A8: Collections from Customers | B8: 48000 | C8: 45000 | D8: 52000 | E8: 47000 | F8: 50000 | G8: 46000 | H8: 53000 | I8: 48000 | J8: 55000 | K8: 49000 | L8: 51000 | M8: 47000 | N8: 54000 | O8: =SUM(B8:N8) -> 645000 | P8: =O8/13 -> 49615.385
A9: Other Income | B9: 2000 | C9: 1500 | D9: 2500 | E9: 1800 | F9: 2200 | G9: 1600 | H9: 2000 | I9: 1700 | J9: 2300 | K9: 1900 | L9: 2100 | M9: 1800 | N9: 2400 | O9: =SUM(B9:N9) -> 25800 | P9: =O9/13 -> 1984.6154
A10: Total Inflows | B10: =SUM(B8:B9) -> 50000 | C10: =SUM(C8:C9) -> 46500 | D10: =SUM(D8:D9) -> 54500 | E10: =SUM(E8:E9) -> 48800 | F10: =SUM(F8:F9) -> 52200 | G10: =SUM(G8:G9) -> 47600 | H10: =SUM(H8:H9) -> 55000 | I10: =SUM(I8:I9) -> 49700 | ... O10: =SUM(O8:O9) -> 670800 | P10: =O10/13 -> 51600
A12: CASH OUTFLOWS
A13: Payroll (Bi-weekly) | B13: 0 | C13: 115000 | D13: 0 | E13: 115000 | F13: 0 | G13: 117000 | H13: 0 | I13: 117000 | J13: 0 | K13: 118000 | L13: 0 | M13: 118000 | N13: 0 | O13: =SUM(B13:N13) -> 700000 | P13: =O13/13 -> 53846.154
A14: Rent & Facilities | B14: 12000 | C14: 0 | D14: 0 | E14: 0 | F14: 12000 | G14: 0 | H14: 0 | I14: 0 | J14: 12000 | K14: 0 | L14: 0 | M14: 0 | N14: 12000 | O14: =SUM(B14:N14) -> 48000 | P14: =O14/13 -> 3692.3077
A15: Marketing Spend | B15: 8000 | C15: 8000 | D15: 8500 | E15: 8000 | F15: 8500 | G15: 8000 | H15: 7500 | I15: 8000 | J15: 9000 | K15: 8500 | L15: 8000 | M15: 7500 | N15: 8500 | O15: =SUM(B15:N15) -> 106000 | P15: =O15/13 -> 8153.8462
A16: Software & Tools | B16: 5000 | C16: 3500 | D16: 4000 | E16: 3500 | F16: 5500 | G16: 3500 | H16: 4000 | I16: 3500 | J16: 5000 | K16: 3500 | L16: 4000 | M16: 3500 | N16: 5500 | O16: =SUM(B16:N16) -> 54000 | P16: =O16/13 -> 4153.8462
A17: Other Operating Expenses | B17: 5000 | C17: 4500 | D17: 6000 | E17: 5500 | F17: 7000 | G17: 4000 | H17: 5500 | I17: 6500 | J17: 4500 | K17: 5000 | L17: 6000 | M17: 4500 | N17: 5500 | O17: =SUM(B17:N17) -> 69500 | P17: =O17/13 -> 5346.1538
A18: Total Outflows | B18: =SUM(B13:B17) -> 30000 | C18: =SUM(C13:C17) -> 131000 | D18: =SUM(D13:D17) -> 18500 | E18: =SUM(E13:E17) -> 132000 | F18: =SUM(F13:F17) -> 33000 | G18: =SUM(G13:G17) -> 132500 | H18: =SUM(H13:H17) -> 17000 | I18: =SUM(I13:I17) -> 135000 | ... O18: =SUM(O13:O17) -> 977500 | P18: =O18/13 -> 75192.308
A19: NET CASH FLOW | B19: =B10-B18 -> 20000 | C19: =C10-C18 -> -84500 | D19: =D10-D18 -> 36000 | E19: =E10-E18 -> -83200 | F19: =F10-F18 -> 19200 | G19: =G10-G18 -> -84900 | H19: =H10-H18 -> 38000 | I19: =I10-I18 -> -85300 | ... O19: =O10-O18 -> -306700 | P19: =O19/13 -> -23592.308
A20: ENDING CASH BALANCE | B20: =B5+B19 -> 870000 | C20: =C5+C19 -> 785500 | D20: =D5+D19 -> 821500 | E20: =E5+E19 -> 738300 | F20: =F5+F19 -> 757500 | G20: =G5+G19 -> 672600 | H20: =H5+H19 -> 710600 | I20: =I5+I19 -> 625300 | ... N20: =N5+N19 -> 543300 | O20: =N20 -> 543300 | P20: Final
A21: Min Threshold Check ($200k) | B21: =IF(B20<200000,"⚠ BELOW MIN","✓ OK") -> ✓ OK | C21: =IF(C20<200000,"⚠ BELOW MIN","✓ OK") -> ✓ OK | D21: =IF(D20<200000,"⚠ BELOW MIN","✓ OK") -> ✓ OK | E21: =IF(E20<200000,"⚠ BELOW MIN","✓ OK") -> ✓ OK | F21: =IF(F20<200000,"⚠ BELOW MIN","✓ OK") -> ✓ OK | G21: =IF(G20<200000,"⚠ BELOW MIN","✓ OK") -> ✓ OK | H21: =IF(H20<200000,"⚠ BELOW MIN","✓ OK") -> ✓ OK | I21: =IF(I20<200000,"⚠ BELOW MIN","✓ OK") -> ✓ OK | ... N21: =IF(N20<200000,"⚠ BELOW MIN","✓ OK") -> ✓ OK | O21: =COUNTIF(B21:N21,"⚠ BELOW MIN") -> 0 | P21: Alerts

Sheet 7. Scenario Analysis
A1: SCENARIO ANALYSIS TOOL (What-If?) - TechFlow Solutions d.o.o. | FY 2024
A4: SCENARIO SELECTOR | G4: SCENARIO COMPARISON SUMMARY
A5: Select Scenario: | B5: =A9 -> Base Case | C5: insert case | G5: Metric | H5: Base Case | I5: Optimistic | J5: Pessimistic | K5: Crisis
G6: Revenue | H6: =$B$20*(1+B9) -> 2760000 | I6: =$B$20*(1+B10) -> 3120000 | J6: =$B$20*(1+B11) -> 2520000 | K6: =$B$20*(1+B12) -> 2160000
A7: SCENARIO ASSUMPTIONS | G7: Gross Profit | H7: =H6-($B$22*(1+B9*0.4)) -> 2251200 | I7: =I6-($B$22*(1+B10*0.4)) -> 2582400 | J7: =J6-($B$22*(1+B11*0.4)) -> 2030400 | K7: =K6-($B$22*(1+B12*0.4)) -> 1699200
A8: Scenario | B8: Revenue Growth | C8: OpEx Change | D8: Churn Rate | E8: Description | G8: Operating Expenses | H8: =$B$31*(1+C9) -> 1998000 | I8: =$B$31*(1+C10) -> 2072000 | J8: =$B$31*(1+C11) -> 1942500 | K8: =$B$31*(1+C12) -> 1572500
A9: Base Case | B9: 0.15 | C9: 0.08 | D9: 0.04 | E9: Expected performance with moderate growth | G9: EBITDA | H9: =H7-H8 -> 253200 | I9: =I7-I8 -> 510400 | J9: =J7-J8 -> 87900 | K9: =K7-K8 -> 126700
A10: Optimistic | B10: 0.3 | C10: 0.12 | D10: 0.02 | E10: Strong market, high retention, accelerated growth | G10: EBITDA Margin | H10: =H9/H6 -> 0.09173913 | I10: =I9/I6 -> 0.16358974 | J10: =J9/J6 -> 0.034880952 | K10: =K9/K6 -> 0.058657407
A11: Pessimistic | B11: 0.05 | C11: 0.05 | D11: 0.07 | E11: Market headwinds, increased competition | G11: Net Income | H11: =H9-$B$36 -> 208200 | I11: =I9-$B$36 -> 465400 | J11: =J9-$B$36 -> 42900 | K11: =K9-$B$36 -> 81700
A12: Crisis Mode | B12: -0.1 | C12: -0.15 | D12: 0.12 | E12: Severe downturn, cost cutting required | G12: Net Margin | H12: =H11/H6 -> 0.075434783 | I12: =I11/I6 -> 0.14916667 | J12: =J11/J6 -> 0.01702381 | K12: =K11/K6 -> 0.037824074
G13: Cash Impact (Est.) | H13: =H11*0.9 -> 187380 | I13: =I11*0.9 -> 418860 | J13: =J11*0.9 -> 38610 | K13: =K11*0.9 -> 73530
A14: DYNAMIC INCOME STATEMENT
A15: Line Item | B15: Base Budget | C15: Scenario Result | D15: Variance ($) | E15: Variance (%)
A16: REVENUE
A17: Subscription Revenue | B17: 2000000 | C17: =B17*(1+_xlfn.XLOOKUP($B$5,$A$9:$A$12,$B$9:$B$12,0)) -> 2300000 | D17: =C17-B17 -> 300000 | E17: =IF(B17=0,0,D17/B17) -> 0.15
A18: Professional Services | B18: 350000 | C18: =B18*(1+_xlfn.XLOOKUP($B$5,$A$9:$A$12,$B$9:$B$12,0)*0.5) -> 376250 | D18: =C18-B18 -> 26250 | E18: =IF(B18=0,0,D18/B18) -> 0.075
A19: Other Revenue | B19: 50000 | C19: =B19*(1+_xlfn.XLOOKUP($B$5,$A$9:$A$12,$B$9:$B$12,0)*0.3) -> 52250 | D19: =C19-B19 -> 2250 | E19: =IF(B19=0,0,D19/B19) -> 0.045
A20: TOTAL REVENUE | B20: =SUM(B17:B19) -> 2400000 | C20: =SUM(C17:C19) -> 2728500 | D20: =C20-B20 -> 328500 | E20: =IF(B20=0,0,D20/B20) -> 0.136875
A22: Cost of Revenue | B22: 480000 | C22: =B22*(1+_xlfn.XLOOKUP($B$5,$A$9:$A$12,$B$9:$B$12,0)*0.4) -> 508800 | D22: =C22-B22 -> 28800 | E22: =IF(B22=0,0,D22/B22) -> 0.06
A23: GROSS PROFIT | B23: =B20-B22 -> 1920000 | C23: =C20-C22 -> 2219700 | D23: =C23-B23 -> 299700 | E23: =IF(B23=0,0,D23/B23) -> 0.15609375
A24: Gross Margin % | B24: =B23/B20 -> 0.8 | C24: =C23/C20 -> 0.81352391
A26: OPERATING EXPENSES
A27: Salaries & Benefits | B27: 1100000 | C27: =B27*(1+_xlfn.XLOOKUP($B$5,$A$9:$A$12,$C$9:$C$12,0)) -> 1188000 | D27: =C27-B27 -> 88000 | E27: =IF(B27=0,0,D27/B27) -> 0.08
A28: Marketing & Sales | B28: 280000 | C28: =B28*(1+_xlfn.XLOOKUP($B$5,$A$9:$A$12,$C$9:$C$12,0)) -> 302400 | D28: =C28-B28 -> 22400 | E28: =IF(B28=0,0,D28/B28) -> 0.08
A29: R&D | B29: 320000 | C29: =B29*(1+_xlfn.XLOOKUP($B$5,$A$9:$A$12,$C$9:$C$12,0)) -> 345600 | D29: =C29-B29 -> 25600 | E29: =IF(B29=0,0,D29/B29) -> 0.08
A30: G&A | B30: 150000 | C30: =B30*(1+_xlfn.XLOOKUP($B$5,$A$9:$A$12,$C$9:$C$12,0)) -> 162000 | D30: =C30-B30 -> 12000 | E30: =IF(B30=0,0,D30/B30) -> 0.08
A31: TOTAL OPEX | B31: =SUM(B27:B30) -> 1850000 | C31: =SUM(C27:C30) -> 1998000 | D31: =C31-B31 -> 148000 | E31: =IF(B31=0,0,D31/B31) -> 0.08
A33: EBITDA | B33: =B23-B31 -> 70000 | C33: =C23-C31 -> 221700 | D33: =C33-B33 -> 151700 | E33: =IF(B33=0,0,D33/B33) -> 2.1671429
A34: EBITDA Margin % | B34: =B33/B20 -> 0.029166667 | C34: =C33/C20 -> 0.081253436
A36: D&A | B36: 45000 | C36: 45000 | D36: =C36-B36 -> 0 | E36: =IF(B36=0,0,D36/B36) -> 0
A37: NET INCOME | B37: =B33-B36 -> 25000 | C37: =C33-C36 -> 176700 | D37: =C37-B37 -> 151700 | E37: =IF(B37=0,0,D37/B37) -> 6.068
